./.gitignore
./.python-version
./PKG-INFO
./README.md
./main.py
./pyproject.toml
./pyrightconfig.json
./.claude/settings.local.json
./.claude/commands/create-issue.md
./.claude/commands/github-pypi-release.md
./.github/dependabot.yml
./.github/workflows/dependabot-auto-merge.yml
./.github/workflows/publish.yml
./.plans/implement-bump-version-cli-with-interactive-prompts.md
pybumpit-1.0.2.dist-info/METADATA
pybumpit-1.0.2.dist-info/WHEEL
pybumpit-1.0.2.dist-info/entry_points.txt
pybumpit-1.0.2.dist-info/RECORD
