Metadata-Version: 2.4
Name: pybumpit
Version: 1.0.2
Summary: npm version-like tool for Python projects
Requires-Python: >=3.12
Requires-Dist: python-clack
Requires-Dist: tomlkit
